<odoo>
    <record id="inmobiliaria_upo_trabajador_form_view" model="ir.ui.view">
        <field name="name">inmobiliaria_upo.trabajador.form</field>
        <field name="model">inmobiliaria_upo.trabajador</field>
        <field name="arch" type="xml">
            <form string="Trabajador">
                <sheet layout="auto">
                    <group>
                        <field name="name" />
                        <field name="sueldo" /> 
                        <field name="ids_Empresas" widget="many2one" />
                    </group>
                </sheet>
            </form>
        </field>
    </record>

    <record id="inmobiliaria_upo_trabajador_tree_view" model="ir.ui.view">
    <field name="name">inmobiliaria_upo.trabajador.tree</field>
    <field name="model">inmobiliaria_upo.trabajador</field>
    <field name="arch" type="xml">
      <tree string="tree_string">
        <field name="name" />
        <!--
        Faltarian ciertos campos de haber heredado del modulo persona
        <field name="sNombre" />
        <field name="sApellidoUno" />
        <field name="sApellidoDos" />
        <field name="iEdad" />
        <field name="sEmail" />
        <field name="iTelefono" />
        -->
      </tree>
    </field>
  </record>

  
<record id="inmobiliaria_upo_trabajador_graph_view" model="ir.ui.view" >
  <field name="name">inmobiliaria_upo.trabajador.graph</field>
  <field name="model">inmobiliaria_upo.trabajador</field>
  <field name="arch" type="xml">
    <graph string="Sueldos" type="pie">
      <field name="sueldo" type="row"/>
    </graph>
  </field>
</record>

  <record id="trabajador_list_action" model="ir.actions.act_window">
      <field name="name">Trabajador</field>
      <field name="res_model">inmobiliaria_upo.trabajador</field>
      <field name="view_mode">tree,form,graph</field>
      <field name="help" type="html">
        <p class="o_view_nocontent_smiling_face">Create the first class</p>
      </field>
  </record>
</odoo>